git_adapter/__init__.py
git_adapter/git.py
git_adapter-0.3.0.dist-info/LICENSE
git_adapter-0.3.0.dist-info/METADATA
git_adapter-0.3.0.dist-info/WHEEL
git_adapter-0.3.0.dist-info/top_level.txt
git_adapter-0.3.0.dist-info/RECORD
