Metadata-Version: 2.1
Name: git-adapter
Version: 0.3.0
Summary: A Python interface to the Git command line.
Home-page: https://gitlab.com/wdobler/git-adapter.git
Author: Wolfgang Dobler
Author-email: wdobler@gmail.com
Classifier: Programming Language :: Python :: 3
Classifier: License :: OSI Approved :: MIT License
Classifier: Operating System :: OS Independent
Classifier: Topic :: Software Development :: Version Control :: Git
Classifier: Topic :: Utilities
Classifier: Development Status :: 4 - Beta
Requires-Python: >=3.6.9
License-File: LICENSE
